confluence/__init__.py
confluence/client.py
confluence/exceptions/__init__.py
confluence/exceptions/authenticationerror.py
confluence/exceptions/generalerror.py
confluence/exceptions/permissionerror.py
confluence/exceptions/resourcenotfound.py
confluence/exceptions/valuetoolong.py
confluence/exceptions/versionconflict.py
confluence/models/__init__.py
confluence/models/auditrecord.py
confluence/models/content.py
confluence/models/contentbody.py
confluence/models/contenthistory.py
confluence/models/group.py
confluence/models/icon.py
confluence/models/label.py
confluence/models/longtask.py
confluence/models/space.py
confluence/models/user.py
confluence/models/version.py
integration_tests/__init__.py
integration_tests/config.py
integration_tests/test_attachment_operations.py
integration_tests/test_authentication_error.py
integration_tests/test_content_history_operations.py
integration_tests/test_content_operations.py
integration_tests/test_content_property_operations.py
integration_tests/test_context_managed_client.py
integration_tests/test_label_operations.py
integration_tests/test_space_operations.py
integration_tests/test_watch_operations.py
tests/models/__init__.py
tests/models/test_attachment.py
tests/models/test_auditrecord.py
tests/models/test_comment.py
tests/models/test_content_property.py
tests/models/test_group.py
tests/models/test_icon.py
tests/models/test_label.py
tests/models/test_longtask.py
tests/models/test_page.py
tests/models/test_space.py
tests/models/test_user.py
tests/models/test_version.py
confluence_rest_library-1.2.2.dist-info/LICENSE
confluence_rest_library-1.2.2.dist-info/METADATA
confluence_rest_library-1.2.2.dist-info/WHEEL
confluence_rest_library-1.2.2.dist-info/top_level.txt
confluence_rest_library-1.2.2.dist-info/RECORD
