Metadata-Version: 2.1
Name: confluence-rest-library
Version: 1.2.2
Summary: A simple wrapper around the Confluence REST API.
Home-page: https://github.com/DaveTCode/confluence-python-lib
Author: David Tyler
Author-email: davet.code@gmail.com
License: UNKNOWN
Keywords: confluence
Platform: UNKNOWN
Classifier: Development Status :: 5 - Production/Stable
Classifier: Intended Audience :: Developers
Classifier: License :: OSI Approved :: MIT License
Classifier: Programming Language :: Python :: 2.7
Classifier: Programming Language :: Python :: 3.5
Classifier: Programming Language :: Python :: 3.6
Classifier: Programming Language :: Python :: 3.7
Requires-Python: >=2.7,!=3.0,!=3.1,!=3.2,!=3.3,!=3.4
Requires-Dist: requests (<3.0.0a0,>=2.19.1)
